MANIFEST.in
README.md
setup.cfg
setup.py
transcribe-compare
transcribe_compare.egg-info/PKG-INFO
transcribe_compare.egg-info/SOURCES.txt
transcribe_compare.egg-info/dependency_links.txt
transcribe_compare.egg-info/requires.txt
transcribe_compare.egg-info/top_level.txt
transcription_compare/__init__.py
transcription_compare/examples_nlkt.py
transcription_compare/tokens.py
transcription_compare/transcribe-compare-with-digit.py
transcription_compare/ukk_matrix.py
transcription_compare/levenshtein_distance_calculator/__init__.py
transcription_compare/levenshtein_distance_calculator/abstract_levenshtein_dsitance_calculator.py
transcription_compare/levenshtein_distance_calculator/ukk_levenshtein_distance_calculator.py
transcription_compare/local_optimizer/__init__.py
transcription_compare/local_optimizer/digit_test.py
transcription_compare/local_optimizer/digit_util.py
transcription_compare/local_optimizer/local_cer_optimizer.py
transcription_compare/local_optimizer/local_optimizer.py
transcription_compare/results/__init__.py
transcription_compare/results/aligned_token_classification.py
transcription_compare/results/aligned_token_classification_old.py
transcription_compare/results/aligned_token_classification_test.py
transcription_compare/results/aligned_token_classifier.py
transcription_compare/results/alignment_result.py
transcription_compare/results/get_filter_files.py
transcription_compare/results/in_wiki_not_in_wordnet.csv
transcription_compare/results/multi_result.old.py
transcription_compare/results/multi_result.py
transcription_compare/results/pkg_test.py
transcription_compare/results/result.py
transcription_compare/results/names_csv/all_names.csv
transcription_compare/results/names_csv/female_first.csv
transcription_compare/results/names_csv/filter_all_names.csv
transcription_compare/results/names_csv/filter_female_first_names.csv
transcription_compare/results/names_csv/filter_male_first_names.csv
transcription_compare/results/names_csv/male_first.csv
transcription_compare/results/names_csv/same_meaning.csv
transcription_compare/tests/__init__.py
transcription_compare/tests/sandbox.py
transcription_compare/tests/testcases.py
