Metadata-Version: 2.1
Name: transcribe-compare
Version: 0.2.4
Summary: Voicegain Compare transcription
Home-page: UNKNOWN
Author: Huishen Zhan, Kuo Zhang, Jacek Jarmulak
Author-email: huishen@voicegain.ai, kuo@voicegain.ai, jacek@voicegain.ai
License: UNKNOWN
Download-URL: https://github.com/voicegain/transcription-compare/archive/0.2.4.tar.gz
Platform: UNKNOWN
